{"id":195,"photo":"12744.jpg","web_name":"Nugent","event_explain":[["Minutes played",7,1]],"fixture_history":{"all":[["16 Aug 15:00",1,"EVE(H) 2-2",90,0,0,0,2,0,0,0,0,0,0,0,7,4,0,55,2],["23 Aug 15:00",2,"CHE(A) 0-2",90,0,0,0,2,0,0,0,0,0,0,0,9,0,-6229,55,2],["31 Aug 16:00",3,"ARS(H) 1-1",90,0,0,0,1,0,0,0,0,0,0,0,7,1,-7564,54,2],["13 Sep 15:00",4,"STK(A) 1-0",90,0,0,1,0,0,0,0,0,0,0,0,18,3,-8946,53,2],["21 Sep 13:30",5,"MUN(H) 5-3",74,1,0,0,3,0,0,0,0,0,0,0,30,34,-4362,53,6],["27 Sep 15:00",6,"CRY(A) 0-2",90,0,0,0,2,0,0,0,0,0,0,0,0,8,-925,52,2],["04 Oct 15:00",7,"BUR(H) 2-2",28,0,0,0,1,0,0,0,1,0,0,0,3,0,-982,52,0],["18 Oct 15:00",8,"NEW(A) 0-1",35,0,0,0,1,0,0,0,0,0,0,0,5,3,-3463,51,1],["25 Oct 17:30",9,"SWA(A) 0-2",90,0,0,0,2,0,0,0,0,0,0,0,5,7,-2433,51,2],["01 Nov 15:00",10,"WBA(H) 0-1",67,0,0,0,1,0,0,0,0,0,0,0,-1,2,-1027,50,2],["08 Nov 15:00",11,"SOU(A) 0-2",0,0,0,0,0,0,0,0,0,0,0,0,0,0,-944,50,0],["22 Nov 15:00",12,"SUN(H) 0-0",19,0,0,0,0,0,0,0,0,0,0,0,-3,1,-910,49,1],["29 Nov 15:00",13,"QPR(A) 2-3",31,0,0,0,1,0,0,0,1,0,0,0,3,-4,-486,49,0],["02 Dec 19:45",14,"LIV(H) 1-3",0,0,0,0,0,0,0,0,0,0,0,0,0,0,-487,49,0],["07 Dec 16:00",15,"AVL(A) 1-2",45,0,0,0,1,0,0,0,0,0,0,0,9,4,-488,49,1],["13 Dec 15:00",16,"MCI(H) 0-1",0,0,0,0,0,0,0,0,0,0,0,0,0,0,-336,49,0],["20 Dec 15:00",17,"WHU(A) 0-2",29,0,0,0,0,0,0,0,0,0,0,0,6,6,-301,49,1],["26 Dec 15:00",18,"TOT(H) 1-2",74,0,0,0,2,0,0,0,0,0,0,0,-1,4,-233,49,2],["28 Dec 15:00",19,"HUL(A) 1-0",90,0,1,1,0,0,0,0,0,0,0,0,25,17,-73,49,5],["01 Jan 15:00",20,"LIV(A) 2-2",54,1,0,0,1,0,0,0,0,0,0,1,28,25,-61,49,6],["10 Jan 15:00",21,"AVL(H) 1-0",90,0,0,1,0,0,0,0,0,0,0,0,7,3,294,49,2],["17 Jan 15:00",22,"STK(H) 0-1",70,0,0,0,1,0,0,0,0,0,0,0,-1,2,-108,49,2],["31 Jan 15:00",23,"MUN(A) 1-3",29,0,0,0,0,0,0,0,0,0,0,0,1,3,-352,49,1],["07 Feb 15:00",24,"CRY(H) 0-1",70,0,0,0,1,0,0,0,0,0,0,0,3,7,-167,49,2],["10 Feb 19:45",25,"ARS(A) 1-2",5,0,0,0,0,0,0,0,0,0,0,0,0,2,-77,49,1],["22 Feb 14:05",26,"EVE(A) 2-2",29,1,0,0,1,0,0,0,0,0,0,0,23,24,-145,49,5],["04 Mar 19:45",28,"MCI(A) 0-2",34,0,0,0,1,0,0,0,0,0,0,0,1,2,-30,49,1],["14 Mar 15:00",29,"HUL(H) 0-0",7,0,0,0,0,0,0,0,0,0,0,0,-3,1,-16,49,1]],"summary":[[26,"EVE (A)",5],[28,"MCI (A)",1],[29,"HUL (H)",1]]},"season_history":[["2007/08",625,0,1,0,7,0,0,0,0,0,0,0,0,0,61,23],["2008/09",1058,3,1,0,15,0,0,0,1,0,0,2,0,0,54,44],["2009/10",1907,6,3,0,46,0,0,0,0,0,0,6,0,0,50,92]],"fixtures":{"all":[["21 Mar 15:00","Gameweek 30","Spurs (A)"],["04 Apr 15:00","Gameweek 31","West Ham (H)"],["11 Apr 15:00","Gameweek 32","West Brom (A)"],["18 Apr 15:00","Gameweek 33","Swansea (H)"],["25 Apr 15:00","Gameweek 34","Burnley (A)"],["29 Apr 19:45","Gameweek 34","Chelsea (H)"],["02 May 15:00","Gameweek 35","Newcastle (H)"],["09 May 15:00","Gameweek 36","Southampton (H)"],["16 May 15:00","Gameweek 37","Sunderland (A)"],["24 May 15:00","Gameweek 38","QPR (H)"]],"summary":[[30,"TOT (A)","21 Mar 15:00"],[31,"WHU (H)","04 Apr 15:00"],[32,"WBA (A)","11 Apr 15:00"]]},"event_total":1,"type_name":"Forward","team_name":"Leicester","selected_by":"0.4","total_points":52,"current_fixture":"Hull (H)","next_fixture":"Spurs (A)","team_code":13,"news":"","team_id":8,"status":"a","code":12744,"first_name":"David","second_name":"Nugent","now_cost":49,"chance_of_playing_this_round":100,"chance_of_playing_next_round":100,"value_form":"0.5","value_season":"10.6","cost_change_start":-6,"cost_change_event":0,"cost_change_start_fall":6,"cost_change_event_fall":0,"in_dreamteam":false,"dreamteam_count":0,"selected_by_percent":"0.4","form":"2.3","transfers_out":51033,"transfers_in":10081,"transfers_out_event":45,"transfers_in_event":13,"loans_in":0,"loans_out":0,"loaned_in":0,"loaned_out":0,"event_points":1,"points_per_game":"2.1","ep_this":"2.3","ep_next":"2.3","special":false,"minutes":1420,"goals_scored":3,"assists":1,"clean_sheets":3,"goals_conceded":24,"own_goals":0,"penalties_saved":0,"penalties_missed":0,"yellow_cards":2,"red_cards":0,"saves":0,"bonus":1,"ea_index":181,"bps":159,"element_type":4,"team":8}
