{"id":308,"photo":"45268.jpg","web_name":"Sissoko","event_explain":[["Yellow cards",1,-1],["Minutes played",90,2]],"fixture_history":{"all":[["17 Aug 16:00",1,"MCI(H) 0-2",90,0,0,0,2,0,0,0,0,0,0,0,0,12,0,60,2],["23 Aug 12:45",2,"AVL(A) 0-0",90,0,0,1,0,0,0,0,0,0,0,0,9,8,-2578,60,3],["30 Aug 15:00",3,"CRY(H) 3-3",90,0,0,0,3,0,0,0,0,0,0,0,6,7,-3001,60,2],["13 Sep 15:00",4,"SOU(A) 0-4",89,0,0,0,3,0,0,0,0,0,0,0,12,7,-9683,60,2],["20 Sep 15:00",5,"HUL(H) 2-2",90,0,0,0,2,0,0,0,1,0,0,0,16,12,-6998,59,1],["29 Sep 20:00",6,"STK(A) 0-1",90,0,0,0,1,0,0,0,0,0,0,0,3,7,-4745,59,2],["04 Oct 15:00",7,"SWA(A) 2-2",90,0,0,0,2,0,0,0,1,0,0,0,7,5,-3253,58,1],["18 Oct 15:00",8,"LEI(H) 1-0",90,0,0,1,0,0,0,0,0,0,0,0,24,10,-2955,58,3],["26 Oct 13:30",9,"TOT(A) 2-1",90,0,0,0,1,0,0,0,0,0,0,0,16,5,-2183,58,2],["01 Nov 12:45",10,"LIV(H) 1-0",90,0,1,1,0,0,0,0,1,0,0,0,16,6,230,58,5],["09 Nov 13:30",11,"WBA(A) 2-0",90,0,0,1,0,0,0,0,0,0,0,0,17,11,2911,58,3],["22 Nov 15:00",12,"QPR(H) 1-0",90,1,0,1,0,0,0,0,1,0,0,3,34,38,8441,58,10],["29 Nov 15:00",13,"WHU(A) 0-1",75,0,0,0,1,0,0,0,0,1,0,0,-1,0,30158,58,-1],["02 Dec 19:45",14,"BUR(A) 1-1",0,0,0,0,0,0,0,0,0,0,0,0,0,0,-20819,58,0],["06 Dec 12:45",15,"CHE(H) 2-1",90,0,1,0,1,0,0,0,1,0,0,0,18,20,-1885,58,4],["13 Dec 17:30",16,"ARS(A) 1-4",0,0,0,0,0,0,0,0,0,0,0,0,0,0,-8957,58,0],["21 Dec 13:30",17,"SUN(H) 0-1",90,0,0,0,1,0,0,0,0,0,0,0,15,16,1647,58,2],["26 Dec 15:00",18,"MUN(A) 1-3",90,0,0,0,3,0,0,0,0,0,0,0,13,10,-1151,58,2],["28 Dec 16:15",19,"EVE(H) 3-2",90,0,0,0,2,0,0,0,0,0,0,0,19,8,-168,58,2],["01 Jan 15:00",20,"BUR(H) 3-3",90,1,0,0,3,0,0,0,0,0,0,2,29,29,2176,58,9],["10 Jan 15:00",21,"CHE(A) 0-2",83,0,0,0,2,0,0,0,0,0,0,0,9,5,-3993,58,2],["17 Jan 17:30",22,"SOU(H) 1-2",90,0,0,0,2,0,0,0,0,0,0,0,3,8,1473,58,2],["31 Jan 12:45",23,"HUL(A) 3-0",90,0,0,1,0,0,0,0,0,0,0,0,8,11,1177,58,3],["08 Feb 14:05",24,"STK(H) 1-1",90,0,1,0,1,0,0,0,0,0,0,2,17,28,1264,58,7],["11 Feb 20:00",25,"CRY(A) 1-1",90,0,0,0,1,0,0,0,0,0,0,0,8,4,797,58,2],["21 Feb 17:30",26,"MCI(A) 0-5",90,0,0,0,5,0,0,0,0,0,0,0,0,12,-964,58,2],["28 Feb 15:00",27,"AVL(H) 1-0",90,0,0,1,0,0,0,0,0,0,0,0,17,15,5928,58,3],["04 Mar 19:45",28,"MUN(H) 0-1",90,0,0,0,1,0,0,0,0,0,0,0,8,18,-2666,58,2],["15 Mar 16:00",29,"EVE(A) 0-3",90,0,0,0,3,0,0,0,1,0,0,0,15,10,-2621,58,1]],"summary":[[27,"AVL (H)",3],[28,"MUN (H)",2],[29,"EVE (A)",1]]},"season_history":[["2012/13",1068,3,3,1,25,0,0,0,2,0,0,6,164,0,54,53],["2013/14",3031,3,6,10,49,0,0,0,8,0,0,6,539,111,53,109]],"fixtures":{"all":[["21 Mar 15:00","Gameweek 30","Arsenal (H)"],["05 Apr 16:00","Gameweek 31","Sunderland (A)"],["13 Apr 20:00","Gameweek 32","Liverpool (A)"],["19 Apr 16:00","Gameweek 33","Spurs (H)"],["25 Apr 15:00","Gameweek 34","Swansea (H)"],["02 May 15:00","Gameweek 35","Leicester (A)"],["09 May 15:00","Gameweek 36","West Brom (H)"],["16 May 15:00","Gameweek 37","QPR (A)"],["24 May 15:00","Gameweek 38","West Ham (H)"]],"summary":[[30,"ARS (H)","21 Mar 15:00"],[31,"SUN (A)","05 Apr 16:00"],[32,"LIV (A)","13 Apr 20:00"]]},"event_total":1,"type_name":"Midfielder","team_name":"Newcastle","selected_by":"1.9","total_points":78,"current_fixture":"Everton (A)","next_fixture":"Arsenal (H)","team_code":4,"news":"","team_id":12,"status":"a","code":45268,"first_name":"Moussa","second_name":"Sissoko","now_cost":58,"chance_of_playing_this_round":100,"chance_of_playing_next_round":100,"value_form":"0.3","value_season":"13.4","cost_change_start":-2,"cost_change_event":0,"cost_change_start_fall":2,"cost_change_event_fall":0,"in_dreamteam":false,"dreamteam_count":1,"selected_by_percent":"1.9","form":"2.0","transfers_out":118907,"transfers_in":95668,"transfers_out_event":996,"transfers_in_event":175,"loans_in":0,"loans_out":0,"loaned_in":0,"loaned_out":0,"event_points":1,"points_per_game":"2.9","ep_this":"2.0","ep_next":"2.0","special":false,"minutes":2407,"goals_scored":2,"assists":3,"clean_sheets":7,"goals_conceded":40,"own_goals":0,"penalties_saved":0,"penalties_missed":0,"yellow_cards":6,"red_cards":1,"saves":0,"bonus":7,"ea_index":338,"bps":322,"element_type":3,"team":12}
